LICENSE
MANIFEST.in
README.rst
setup.cfg
setup.py
mailthon/__init__.py
mailthon/api.py
mailthon/enclosure.py
mailthon/envelope.py
mailthon/headers.py
mailthon/helpers.py
mailthon/middleware.py
mailthon/postman.py
mailthon/response.py
mailthon.egg-info/PKG-INFO
mailthon.egg-info/SOURCES.txt
mailthon.egg-info/dependency_links.txt
mailthon.egg-info/not-zip-safe
mailthon.egg-info/pbr.json
mailthon.egg-info/top_level.txt