Metadata-Version: 1.1
Name: mailthon
Version: 0.1.1
Summary: Elegant email library
Home-page: https://github.com/eugene-eeo/mailthon/
Author: Eeo Jun
Author-email: packwolf58@gmail.com
License: UNKNOWN
Platform: any
Classifier: Development Status :: 3 - Alpha
Classifier: Intended Audience :: Developers
Classifier: License :: OSI Approved
Classifier: License :: OSI Approved :: MIT License
Classifier: Operating System :: OS Independent
Classifier: Programming Language :: Python
Classifier: Programming Language :: Python :: 2
Classifier: Programming Language :: Python :: 3
Classifier: Topic :: Software Development :: Libraries :: Python Modules
